{
    "dao_symex_path_1.json": {
        "file_name": "",
        "from_function": "setup",
        "to_function": "withdraw",
        "bug_type": "dao",
        "src_node": "\"BlockID: 531\nCall context: \nNone\nENTRY_POINT None\"",
        "dest_node": [
            "\"BlockID: 548\nCall context: \nTrue\ncoreContract := candidateContract\npluginsContract := _pluginsContract\""
        ],
        "executable_instructions": 71,
        "state_variable": "coreContract",
        "error": "",
        "result": "",
        "execution_details": ""
    },
    "dao_symex_path_2.json": {
        "file_name": "",
        "from_function": "setup",
        "to_function": "withdraw",
        "bug_type": "dao",
        "src_node": "\"BlockID: 550\nCall context: \nNone\nENTRY_POINT None\"",
        "dest_node": [
            "\"BlockID: 567\nCall context: \nTrue\ncoreContract := candidateContract\npluginsContract := _pluginsContract\""
        ],
        "executable_instructions": 71,
        "state_variable": "coreContract",
        "error": "",
        "result": "",
        "execution_details": ""
    }
}