{
    "dao_symex_path_1.json": {
        "file_name": "",
        "from_function": "claimToken",
        "to_function": "initialize",
        "bug_type": "dao",
        "src_node": "\"BlockID: 792\nCall context: \nNone\nENTRY_POINT None\"",
        "dest_node": [
            "\"BlockID: 910\nCall context: \nTrue\nTMP_113 = CONVERT this to address\nTMP_114(uint256) = HIGH_LEVEL_CALL, dest:token(IERC20), function:balanceOf, arguments:['TMP_113']  \""
        ],
        "executable_instructions": 435,
        "state_variable": "token",
        "error": "",
        "result": "",
        "execution_details": ""
    },
    "dao_symex_path_2.json": {
        "file_name": "",
        "from_function": "claimToken",
        "to_function": "initialize",
        "bug_type": "dao",
        "src_node": "\"BlockID: 1002\nCall context: \nNone\nENTRY_POINT None\"",
        "dest_node": [
            "\"BlockID: 1120\nCall context: \nTrue\nTMP_113 = CONVERT this to address\nTMP_114(uint256) = HIGH_LEVEL_CALL, dest:token(IERC20), function:balanceOf, arguments:['TMP_113']  \""
        ],
        "executable_instructions": 435,
        "state_variable": "token",
        "error": "",
        "result": "",
        "execution_details": ""
    },
    "dao_symex_path_3.json": {
        "file_name": "",
        "from_function": "claimToken",
        "to_function": "initialize",
        "bug_type": "dao",
        "src_node": "\"BlockID: 1212\nCall context: \nNone\nENTRY_POINT None\"",
        "dest_node": [
            "\"BlockID: 1332\nCall context: \nNone\nclaimedTokens := TMP_115\nTMP_116(bool) = HIGH_LEVEL_CALL, dest:token(IERC20), function:transfer, arguments:['releaseWallet', 'toClaim']  \""
        ],
        "executable_instructions": 456,
        "state_variable": "token",
        "error": "",
        "result": "",
        "execution_details": ""
    },
    "dao_symex_path_4.json": {
        "file_name": "",
        "from_function": "claimToken",
        "to_function": "initialize",
        "bug_type": "dao",
        "src_node": "\"BlockID: 1422\nCall context: \nNone\nENTRY_POINT None\"",
        "dest_node": [
            "\"BlockID: 1542\nCall context: \nNone\nclaimedTokens := TMP_115\nTMP_116(bool) = HIGH_LEVEL_CALL, dest:token(IERC20), function:transfer, arguments:['releaseWallet', 'toClaim']  \""
        ],
        "executable_instructions": 456,
        "state_variable": "token",
        "error": "",
        "result": "",
        "execution_details": ""
    },
    "dao_symex_path_5.json": {
        "file_name": "",
        "from_function": "claimToken",
        "to_function": "initialize",
        "bug_type": "dao",
        "src_node": "\"BlockID: 1632\nCall context: \nNone\nENTRY_POINT None\"",
        "dest_node": [
            "\"BlockID: 1752\nCall context: \nNone\nclaimedTokens := TMP_115\nTMP_116(bool) = HIGH_LEVEL_CALL, dest:token(IERC20), function:transfer, arguments:['releaseWallet', 'toClaim']  \""
        ],
        "executable_instructions": 456,
        "state_variable": "token",
        "error": "",
        "result": "",
        "execution_details": ""
    },
    "dao_symex_path_6.json": {
        "file_name": "",
        "from_function": "claimToken",
        "to_function": "initialize",
        "bug_type": "dao",
        "src_node": "\"BlockID: 1842\nCall context: \nNone\nENTRY_POINT None\"",
        "dest_node": [
            "\"BlockID: 1962\nCall context: \nNone\nclaimedTokens := TMP_115\nTMP_116(bool) = HIGH_LEVEL_CALL, dest:token(IERC20), function:transfer, arguments:['releaseWallet', 'toClaim']  \""
        ],
        "executable_instructions": 456,
        "state_variable": "token",
        "error": "",
        "result": "",
        "execution_details": ""
    },
    "dao_symex_path_7.json": {
        "file_name": "",
        "from_function": "claimToken",
        "to_function": "claimToken",
        "bug_type": "dao",
        "src_node": "\"BlockID: 2052\nCall context: \nNone\nENTRY_POINT None\"",
        "dest_node": [
            "\"BlockID: 2222\nCall context: \nTrue\nTMP_113 = CONVERT this to address\nTMP_114(uint256) = HIGH_LEVEL_CALL, dest:token(IERC20), function:balanceOf, arguments:['TMP_113']  \""
        ],
        "executable_instructions": 584,
        "state_variable": "claimedTokens",
        "error": "",
        "result": "",
        "execution_details": ""
    },
    "dao_symex_path_8.json": {
        "file_name": "",
        "from_function": "claimToken",
        "to_function": "claimToken",
        "bug_type": "dao",
        "src_node": "\"BlockID: 2314\nCall context: \nNone\nENTRY_POINT None\"",
        "dest_node": [
            "\"BlockID: 2486\nCall context: \nNone\nclaimedTokens := TMP_115\nTMP_116(bool) = HIGH_LEVEL_CALL, dest:token(IERC20), function:transfer, arguments:['releaseWallet', 'toClaim']  \""
        ],
        "executable_instructions": 605,
        "state_variable": "claimedTokens",
        "error": "",
        "result": "",
        "execution_details": ""
    },
    "dao_symex_path_9.json": {
        "file_name": "",
        "from_function": "claimToken",
        "to_function": "claimToken",
        "bug_type": "dao",
        "src_node": "\"BlockID: 2576\nCall context: \nNone\nENTRY_POINT None\"",
        "dest_node": [
            "\"BlockID: 2748\nCall context: \nNone\nclaimedTokens := TMP_115\nTMP_116(bool) = HIGH_LEVEL_CALL, dest:token(IERC20), function:transfer, arguments:['releaseWallet', 'toClaim']  \""
        ],
        "executable_instructions": 605,
        "state_variable": "claimedTokens",
        "error": "",
        "result": "",
        "execution_details": ""
    },
    "dao_symex_path_10.json": {
        "file_name": "",
        "from_function": "claimToken",
        "to_function": "claimToken",
        "bug_type": "dao",
        "src_node": "\"BlockID: 2838\nCall context: \nNone\nENTRY_POINT None\"",
        "dest_node": [
            "\"BlockID: 3010\nCall context: \nNone\nclaimedTokens := TMP_115\nTMP_116(bool) = HIGH_LEVEL_CALL, dest:token(IERC20), function:transfer, arguments:['releaseWallet', 'toClaim']  \""
        ],
        "executable_instructions": 605,
        "state_variable": "claimedTokens",
        "error": "",
        "result": "",
        "execution_details": ""
    },
    "dao_symex_path_11.json": {
        "file_name": "",
        "from_function": "claimToken",
        "to_function": "claimToken",
        "bug_type": "dao",
        "src_node": "\"BlockID: 3100\nCall context: \nNone\nENTRY_POINT None\"",
        "dest_node": [
            "\"BlockID: 3272\nCall context: \nNone\nclaimedTokens := TMP_115\nTMP_116(bool) = HIGH_LEVEL_CALL, dest:token(IERC20), function:transfer, arguments:['releaseWallet', 'toClaim']  \""
        ],
        "executable_instructions": 605,
        "state_variable": "claimedTokens",
        "error": "",
        "result": "",
        "execution_details": ""
    },
    "dao_symex_path_12.json": {
        "file_name": "",
        "from_function": "claimToken",
        "to_function": "claimToken",
        "bug_type": "dao",
        "src_node": "\"BlockID: 3362\nCall context: \nNone\nENTRY_POINT None\"",
        "dest_node": [
            "\"BlockID: 3534\nCall context: \nNone\nclaimedTokens := TMP_115\nTMP_116(bool) = HIGH_LEVEL_CALL, dest:token(IERC20), function:transfer, arguments:['releaseWallet', 'toClaim']  \""
        ],
        "executable_instructions": 605,
        "state_variable": "claimedTokens",
        "error": "",
        "result": "",
        "execution_details": ""
    },
    "dao_symex_path_13.json": {
        "file_name": "",
        "from_function": "claimToken",
        "to_function": "claimToken",
        "bug_type": "dao",
        "src_node": "\"BlockID: 3624\nCall context: \nNone\nENTRY_POINT None\"",
        "dest_node": [
            "\"BlockID: 3796\nCall context: \nNone\nclaimedTokens := TMP_115\nTMP_116(bool) = HIGH_LEVEL_CALL, dest:token(IERC20), function:transfer, arguments:['releaseWallet', 'toClaim']  \""
        ],
        "executable_instructions": 605,
        "state_variable": "claimedTokens",
        "error": "",
        "result": "",
        "execution_details": ""
    }
}