{
  "contract": "472a72eb49a2360681ba0673e248f728",
  "tool": "securify",
  "start": 1645675156.5460744,
  "end": 1645675560.5474188,
  "duration": 404.00134444236755,
  "analysis": {
    "/data/472a72eb49a2360681ba0673e248f728.sol:CitizenInterface": {
      "results": {
        "TODReceiver": {
          "violations": [],
          "warnings": [],
          "safe": [],
          "conflicts": []
        },
        "UnhandledException": {
          "violations": [],
          "warnings": [],
          "safe": [],
          "conflicts": []
        },
        "TODTransfer": {
          "violations": [],
          "warnings": [],
          "safe": [],
          "conflicts": []
        },
        "DAO": {
          "violations": [],
          "warnings": [],
          "safe": [],
          "conflicts": []
        },
        "TODAmount": {
          "violations": [],
          "warnings": [],
          "safe": [],
          "conflicts": []
        },
        "MissingInputValidation": {
          "violations": [],
          "warnings": [],
          "safe": [],
          "conflicts": []
        },
        "DAOConstantGas": {
          "violations": [],
          "warnings": [],
          "safe": [],
          "conflicts": []
        },
        "UnrestrictedEtherFlow": {
          "violations": [],
          "warnings": [],
          "safe": [],
          "conflicts": []
        }
      }
    },
    "/data/472a72eb49a2360681ba0673e248f728.sol:Lottery": {
      "results": {
        "TODReceiver": {
          "violations": [
            1354,
            1584,
            1926
          ],
          "warnings": [],
          "safe": [],
          "conflicts": []
        },
        "UnhandledException": {
          "violations": [],
          "warnings": [
            1354,
            1584,
            1926
          ],
          "safe": [],
          "conflicts": []
        },
        "TODTransfer": {
          "violations": [],
          "warnings": [],
          "safe": [],
          "conflicts": [
            1354,
            1584,
            1926
          ]
        },
        "DAO": {
          "violations": [
            1354
          ],
          "warnings": [
            1584,
            1926
          ],
          "safe": [],
          "conflicts": []
        },
        "TODAmount": {
          "violations": [
            1354,
            1584
          ],
          "warnings": [],
          "safe": [
            1926
          ],
          "conflicts": []
        },
        "MissingInputValidation": {
          "violations": [],
          "warnings": [],
          "safe": [],
          "conflicts": []
        },
        "DAOConstantGas": {
          "violations": [],
          "warnings": [],
          "safe": [],
          "conflicts": []
        },
        "UnrestrictedEtherFlow": {
          "violations": [],
          "warnings": [
            1354,
            1584,
            1926
          ],
          "safe": [],
          "conflicts": []
        }
      }
    },
    "/data/472a72eb49a2360681ba0673e248f728.sol:RewardInterface": {
      "results": {
        "TODReceiver": {
          "violations": [
            -1
          ],
          "warnings": [],
          "safe": [],
          "conflicts": []
        },
        "UnhandledException": {
          "violations": [],
          "warnings": [
            -1
          ],
          "safe": [],
          "conflicts": []
        },
        "TODTransfer": {
          "violations": [],
          "warnings": [],
          "safe": [],
          "conflicts": [
            -1
          ]
        },
        "DAO": {
          "violations": [
            -1
          ],
          "warnings": [
            -1
          ],
          "safe": [],
          "conflicts": []
        },
        "TODAmount": {
          "violations": [
            -1
          ],
          "warnings": [],
          "safe": [
            -1
          ],
          "conflicts": []
        },
        "MissingInputValidation": {
          "violations": [],
          "warnings": [],
          "safe": [],
          "conflicts": []
        },
        "DAOConstantGas": {
          "violations": [],
          "warnings": [],
          "safe": [],
          "conflicts": []
        },
        "UnrestrictedEtherFlow": {
          "violations": [],
          "warnings": [
            -1
          ],
          "safe": [],
          "conflicts": []
        }
      }
    },
    "/data/472a72eb49a2360681ba0673e248f728.sol:SafeMath": {
      "results": {
        "TODReceiver": {
          "violations": [
            -1
          ],
          "warnings": [],
          "safe": [],
          "conflicts": []
        },
        "UnhandledException": {
          "violations": [],
          "warnings": [
            -1
          ],
          "safe": [],
          "conflicts": []
        },
        "TODTransfer": {
          "violations": [],
          "warnings": [],
          "safe": [],
          "conflicts": [
            -1
          ]
        },
        "DAO": {
          "violations": [
            -1
          ],
          "warnings": [
            -1
          ],
          "safe": [],
          "conflicts": []
        },
        "TODAmount": {
          "violations": [
            -1
          ],
          "warnings": [],
          "safe": [
            -1
          ],
          "conflicts": []
        },
        "MissingInputValidation": {
          "violations": [],
          "warnings": [],
          "safe": [],
          "conflicts": []
        },
        "DAOConstantGas": {
          "violations": [],
          "warnings": [],
          "safe": [],
          "conflicts": []
        },
        "UnrestrictedEtherFlow": {
          "violations": [],
          "warnings": [
            -1
          ],
          "safe": [],
          "conflicts": []
        }
      }
    },
    "/data/472a72eb49a2360681ba0673e248f728.sol:DevTeamInterface": {
      "results": {
        "TODReceiver": {
          "violations": [],
          "warnings": [],
          "safe": [],
          "conflicts": []
        },
        "UnhandledException": {
          "violations": [],
          "warnings": [],
          "safe": [],
          "conflicts": []
        },
        "TODTransfer": {
          "violations": [],
          "warnings": [],
          "safe": [],
          "conflicts": []
        },
        "DAO": {
          "violations": [],
          "warnings": [],
          "safe": [],
          "conflicts": []
        },
        "TODAmount": {
          "violations": [],
          "warnings": [],
          "safe": [],
          "conflicts": []
        },
        "MissingInputValidation": {
          "violations": [],
          "warnings": [],
          "safe": [],
          "conflicts": []
        },
        "DAOConstantGas": {
          "violations": [],
          "warnings": [],
          "safe": [],
          "conflicts": []
        },
        "UnrestrictedEtherFlow": {
          "violations": [],
          "warnings": [],
          "safe": [],
          "conflicts": []
        }
      }
    },
    "/data/472a72eb49a2360681ba0673e248f728.sol:BankInterface": {
      "results": {
        "TODReceiver": {
          "violations": [],
          "warnings": [],
          "safe": [],
          "conflicts": []
        },
        "UnhandledException": {
          "violations": [],
          "warnings": [],
          "safe": [],
          "conflicts": []
        },
        "TODTransfer": {
          "violations": [],
          "warnings": [],
          "safe": [],
          "conflicts": []
        },
        "DAO": {
          "violations": [],
          "warnings": [],
          "safe": [],
          "conflicts": []
        },
        "TODAmount": {
          "violations": [],
          "warnings": [],
          "safe": [],
          "conflicts": []
        },
        "MissingInputValidation": {
          "violations": [],
          "warnings": [],
          "safe": [],
          "conflicts": []
        },
        "DAOConstantGas": {
          "violations": [],
          "warnings": [],
          "safe": [],
          "conflicts": []
        },
        "UnrestrictedEtherFlow": {
          "violations": [],
          "warnings": [],
          "safe": [],
          "conflicts": []
        }
      }
    },
    "/data/472a72eb49a2360681ba0673e248f728.sol:Helper": {
      "results": {
        "TODReceiver": {
          "violations": [],
          "warnings": [],
          "safe": [],
          "conflicts": []
        },
        "UnhandledException": {
          "violations": [],
          "warnings": [],
          "safe": [],
          "conflicts": []
        },
        "TODTransfer": {
          "violations": [],
          "warnings": [],
          "safe": [],
          "conflicts": []
        },
        "DAO": {
          "violations": [],
          "warnings": [],
          "safe": [],
          "conflicts": []
        },
        "TODAmount": {
          "violations": [],
          "warnings": [],
          "safe": [],
          "conflicts": []
        },
        "MissingInputValidation": {
          "violations": [],
          "warnings": [],
          "safe": [],
          "conflicts": []
        },
        "DAOConstantGas": {
          "violations": [],
          "warnings": [],
          "safe": [],
          "conflicts": []
        },
        "UnrestrictedEtherFlow": {
          "violations": [],
          "warnings": [],
          "safe": [],
          "conflicts": []
        }
      }
    },
    "/data/472a72eb49a2360681ba0673e248f728.sol:F2mInterface": {
      "results": {
        "TODReceiver": {
          "violations": [],
          "warnings": [],
          "safe": [],
          "conflicts": []
        },
        "UnhandledException": {
          "violations": [],
          "warnings": [],
          "safe": [],
          "conflicts": []
        },
        "TODTransfer": {
          "violations": [],
          "warnings": [],
          "safe": [],
          "conflicts": []
        },
        "DAO": {
          "violations": [],
          "warnings": [],
          "safe": [],
          "conflicts": []
        },
        "TODAmount": {
          "violations": [],
          "warnings": [],
          "safe": [],
          "conflicts": []
        },
        "MissingInputValidation": {
          "violations": [],
          "warnings": [],
          "safe": [],
          "conflicts": []
        },
        "DAOConstantGas": {
          "violations": [],
          "warnings": [],
          "safe": [],
          "conflicts": []
        },
        "UnrestrictedEtherFlow": {
          "violations": [],
          "warnings": [],
          "safe": [],
          "conflicts": []
        }
      }
    }
  }
}