{
  "contract": "d4d5ec14521211d26270de052debe5b1",
  "tool": "securify",
  "start": 1645962711.549044,
  "end": 1645962805.193604,
  "duration": 93.64456009864807,
  "analysis": {
    "/data/d4d5ec14521211d26270de052debe5b1.sol:Log": {
      "results": {
        "TODReceiver": {
          "violations": [],
          "warnings": [],
          "safe": [],
          "conflicts": []
        },
        "UnhandledException": {
          "violations": [],
          "warnings": [],
          "safe": [],
          "conflicts": []
        },
        "TODTransfer": {
          "violations": [],
          "warnings": [],
          "safe": [],
          "conflicts": []
        },
        "DAO": {
          "violations": [],
          "warnings": [],
          "safe": [],
          "conflicts": []
        },
        "TODAmount": {
          "violations": [],
          "warnings": [],
          "safe": [],
          "conflicts": []
        },
        "MissingInputValidation": {
          "violations": [],
          "warnings": [],
          "safe": [],
          "conflicts": []
        },
        "DAOConstantGas": {
          "violations": [],
          "warnings": [],
          "safe": [],
          "conflicts": []
        },
        "UnrestrictedEtherFlow": {
          "violations": [],
          "warnings": [],
          "safe": [],
          "conflicts": []
        }
      }
    },
    "/data/d4d5ec14521211d26270de052debe5b1.sol:MONEY_BOX": {
      "results": {
        "TODReceiver": {
          "violations": [],
          "warnings": [
            55
          ],
          "safe": [],
          "conflicts": []
        },
        "UnhandledException": {
          "violations": [],
          "warnings": [
            55,
            58,
            45
          ],
          "safe": [],
          "conflicts": []
        },
        "TODTransfer": {
          "violations": [
            55
          ],
          "warnings": [],
          "safe": [],
          "conflicts": []
        },
        "DAO": {
          "violations": [
            55
          ],
          "warnings": [],
          "safe": [],
          "conflicts": []
        },
        "TODAmount": {
          "violations": [],
          "warnings": [
            55
          ],
          "safe": [],
          "conflicts": []
        },
        "MissingInputValidation": {
          "violations": [
            18,
            10,
            25
          ],
          "warnings": [
            32,
            12,
            38
          ],
          "safe": [
            48
          ],
          "conflicts": []
        },
        "DAOConstantGas": {
          "violations": [],
          "warnings": [],
          "safe": [],
          "conflicts": []
        },
        "UnrestrictedEtherFlow": {
          "violations": [],
          "warnings": [
            58,
            45
          ],
          "safe": [
            55
          ],
          "conflicts": []
        }
      }
    }
  }
}