{
  "contract": "3de7d3ee3f52048c5f65f6a51d724c6e",
  "tool": "securify",
  "start": 1646115150.044927,
  "end": 1646115228.16443,
  "duration": 78.11950302124023,
  "analysis": {
    "/data/3de7d3ee3f52048c5f65f6a51d724c6e.sol:Owned": {
      "results": {
        "TODReceiver": {
          "violations": [
            -1
          ],
          "warnings": [
            -1
          ],
          "safe": [],
          "conflicts": []
        },
        "UnhandledException": {
          "violations": [],
          "warnings": [
            -1
          ],
          "safe": [],
          "conflicts": []
        },
        "TODTransfer": {
          "violations": [],
          "warnings": [
            -1
          ],
          "safe": [],
          "conflicts": [
            -1
          ]
        },
        "DAO": {
          "violations": [],
          "warnings": [
            -1
          ],
          "safe": [],
          "conflicts": []
        },
        "TODAmount": {
          "violations": [
            -1
          ],
          "warnings": [],
          "safe": [],
          "conflicts": []
        },
        "MissingInputValidation": {
          "violations": [
            17
          ],
          "warnings": [
            20,
            4,
            3
          ],
          "safe": [],
          "conflicts": []
        },
        "DAOConstantGas": {
          "violations": [],
          "warnings": [
            -1
          ],
          "safe": [],
          "conflicts": []
        },
        "UnrestrictedEtherFlow": {
          "violations": [],
          "warnings": [
            -1
          ],
          "safe": [
            -1
          ],
          "conflicts": []
        }
      }
    },
    "/data/3de7d3ee3f52048c5f65f6a51d724c6e.sol:HourglassInterface": {
      "results": {
        "TODReceiver": {
          "violations": [
            -1
          ],
          "warnings": [
            -1
          ],
          "safe": [],
          "conflicts": []
        },
        "UnhandledException": {
          "violations": [],
          "warnings": [
            -1
          ],
          "safe": [],
          "conflicts": []
        },
        "TODTransfer": {
          "violations": [],
          "warnings": [
            -1
          ],
          "safe": [],
          "conflicts": [
            -1
          ]
        },
        "DAO": {
          "violations": [],
          "warnings": [
            -1
          ],
          "safe": [],
          "conflicts": []
        },
        "TODAmount": {
          "violations": [
            -1
          ],
          "warnings": [],
          "safe": [],
          "conflicts": []
        },
        "MissingInputValidation": {
          "violations": [],
          "warnings": [],
          "safe": [],
          "conflicts": []
        },
        "DAOConstantGas": {
          "violations": [],
          "warnings": [
            -1
          ],
          "safe": [],
          "conflicts": []
        },
        "UnrestrictedEtherFlow": {
          "violations": [],
          "warnings": [
            -1
          ],
          "safe": [
            -1
          ],
          "conflicts": []
        }
      }
    },
    "/data/3de7d3ee3f52048c5f65f6a51d724c6e.sol:DivGarden": {
      "results": {
        "TODReceiver": {
          "violations": [
            145
          ],
          "warnings": [
            44
          ],
          "safe": [],
          "conflicts": []
        },
        "UnhandledException": {
          "violations": [],
          "warnings": [
            73,
            76,
            145,
            44
          ],
          "safe": [],
          "conflicts": []
        },
        "TODTransfer": {
          "violations": [],
          "warnings": [
            145
          ],
          "safe": [],
          "conflicts": [
            44
          ]
        },
        "DAO": {
          "violations": [],
          "warnings": [
            44
          ],
          "safe": [],
          "conflicts": []
        },
        "TODAmount": {
          "violations": [
            145,
            44
          ],
          "warnings": [],
          "safe": [],
          "conflicts": []
        },
        "MissingInputValidation": {
          "violations": [],
          "warnings": [],
          "safe": [],
          "conflicts": []
        },
        "DAOConstantGas": {
          "violations": [],
          "warnings": [
            145
          ],
          "safe": [],
          "conflicts": []
        },
        "UnrestrictedEtherFlow": {
          "violations": [],
          "warnings": [
            73,
            76
          ],
          "safe": [
            145,
            44
          ],
          "conflicts": []
        }
      }
    }
  }
}