{
  "contract": "a6880c026ef042ede047b4bf3fb21a27",
  "tool": "securify",
  "start": 1646162348.0056832,
  "end": 1646162902.4145842,
  "duration": 554.408900976181,
  "analysis": {
    "/data/a6880c026ef042ede047b4bf3fb21a27.sol:TokenController": {
      "results": {
        "TODReceiver": {
          "violations": [
            -1
          ],
          "warnings": [],
          "safe": [],
          "conflicts": []
        },
        "UnhandledException": {
          "violations": [],
          "warnings": [
            -1
          ],
          "safe": [],
          "conflicts": []
        },
        "TODTransfer": {
          "violations": [],
          "warnings": [],
          "safe": [],
          "conflicts": [
            -1
          ]
        },
        "DAO": {
          "violations": [],
          "warnings": [
            -1
          ],
          "safe": [],
          "conflicts": []
        },
        "TODAmount": {
          "violations": [
            -1
          ],
          "warnings": [],
          "safe": [
            -1
          ],
          "conflicts": []
        },
        "MissingInputValidation": {
          "violations": [],
          "warnings": [],
          "safe": [],
          "conflicts": []
        },
        "DAOConstantGas": {
          "violations": [],
          "warnings": [
            -1
          ],
          "safe": [],
          "conflicts": []
        },
        "UnrestrictedEtherFlow": {
          "violations": [],
          "warnings": [
            -1
          ],
          "safe": [],
          "conflicts": []
        }
      }
    },
    "/data/a6880c026ef042ede047b4bf3fb21a27.sol:Controlled": {
      "results": {
        "TODReceiver": {
          "violations": [],
          "warnings": [],
          "safe": [],
          "conflicts": []
        },
        "UnhandledException": {
          "violations": [],
          "warnings": [],
          "safe": [],
          "conflicts": []
        },
        "TODTransfer": {
          "violations": [],
          "warnings": [],
          "safe": [],
          "conflicts": []
        },
        "DAO": {
          "violations": [],
          "warnings": [],
          "safe": [],
          "conflicts": []
        },
        "TODAmount": {
          "violations": [],
          "warnings": [],
          "safe": [],
          "conflicts": []
        },
        "MissingInputValidation": {
          "violations": [
            38
          ],
          "warnings": [
            26
          ],
          "safe": [],
          "conflicts": []
        },
        "DAOConstantGas": {
          "violations": [],
          "warnings": [],
          "safe": [],
          "conflicts": []
        },
        "UnrestrictedEtherFlow": {
          "violations": [],
          "warnings": [],
          "safe": [],
          "conflicts": []
        }
      }
    },
    "/data/a6880c026ef042ede047b4bf3fb21a27.sol:MiniMeToken": {
      "results": {
        "TODReceiver": {
          "violations": [
            1102,
            1076
          ],
          "warnings": [],
          "safe": [],
          "conflicts": []
        },
        "UnhandledException": {
          "violations": [],
          "warnings": [
            1102,
            480,
            564,
            1076,
            1112,
            694,
            744,
            810,
            622
          ],
          "safe": [],
          "conflicts": []
        },
        "TODTransfer": {
          "violations": [],
          "warnings": [],
          "safe": [],
          "conflicts": [
            1102,
            1076
          ]
        },
        "DAO": {
          "violations": [],
          "warnings": [
            1076
          ],
          "safe": [],
          "conflicts": []
        },
        "TODAmount": {
          "violations": [
            1102
          ],
          "warnings": [],
          "safe": [
            1076
          ],
          "conflicts": []
        },
        "MissingInputValidation": {
          "violations": [],
          "warnings": [],
          "safe": [],
          "conflicts": []
        },
        "DAOConstantGas": {
          "violations": [],
          "warnings": [
            1102
          ],
          "safe": [],
          "conflicts": []
        },
        "UnrestrictedEtherFlow": {
          "violations": [],
          "warnings": [
            1102,
            480,
            564,
            1076,
            1112,
            694,
            744,
            810,
            622
          ],
          "safe": [],
          "conflicts": []
        }
      }
    },
    "/data/a6880c026ef042ede047b4bf3fb21a27.sol:PXP": {
      "results": {
        "TODReceiver": {
          "violations": [
            1308,
            1076,
            1402
          ],
          "warnings": [],
          "safe": [],
          "conflicts": []
        },
        "UnhandledException": {
          "violations": [],
          "warnings": [
            1308,
            896,
            2,
            1076,
            1324,
            22,
            694,
            740,
            240,
            1402,
            480,
            564,
            1412,
            744,
            810,
            622
          ],
          "safe": [],
          "conflicts": []
        },
        "TODTransfer": {
          "violations": [],
          "warnings": [],
          "safe": [],
          "conflicts": [
            1308,
            1076,
            1402
          ]
        },
        "DAO": {
          "violations": [],
          "warnings": [
            1076
          ],
          "safe": [],
          "conflicts": []
        },
        "TODAmount": {
          "violations": [
            1308,
            1402
          ],
          "warnings": [],
          "safe": [
            1076
          ],
          "conflicts": []
        },
        "MissingInputValidation": {
          "violations": [],
          "warnings": [],
          "safe": [],
          "conflicts": []
        },
        "DAOConstantGas": {
          "violations": [],
          "warnings": [
            1308,
            1402
          ],
          "safe": [],
          "conflicts": []
        },
        "UnrestrictedEtherFlow": {
          "violations": [],
          "warnings": [
            1308,
            896,
            2,
            1076,
            1324,
            22,
            694,
            740,
            240,
            1402,
            480,
            564,
            1412,
            744,
            810,
            622
          ],
          "safe": [],
          "conflicts": []
        }
      }
    },
    "/data/a6880c026ef042ede047b4bf3fb21a27.sol:ApproveAndCallFallBack": {
      "results": {
        "TODReceiver": {
          "violations": [],
          "warnings": [],
          "safe": [],
          "conflicts": []
        },
        "UnhandledException": {
          "violations": [],
          "warnings": [],
          "safe": [],
          "conflicts": []
        },
        "TODTransfer": {
          "violations": [],
          "warnings": [],
          "safe": [],
          "conflicts": []
        },
        "DAO": {
          "violations": [],
          "warnings": [],
          "safe": [],
          "conflicts": []
        },
        "TODAmount": {
          "violations": [],
          "warnings": [],
          "safe": [],
          "conflicts": []
        },
        "MissingInputValidation": {
          "violations": [],
          "warnings": [],
          "safe": [],
          "conflicts": []
        },
        "DAOConstantGas": {
          "violations": [],
          "warnings": [],
          "safe": [],
          "conflicts": []
        },
        "UnrestrictedEtherFlow": {
          "violations": [],
          "warnings": [],
          "safe": [],
          "conflicts": []
        }
      }
    },
    "/data/a6880c026ef042ede047b4bf3fb21a27.sol:MiniMeTokenFactory": {
      "results": {
        "TODReceiver": {
          "violations": [
            -1,
            1190
          ],
          "warnings": [],
          "safe": [],
          "conflicts": []
        },
        "UnhandledException": {
          "violations": [],
          "warnings": [
            -1,
            1190,
            1226
          ],
          "safe": [],
          "conflicts": []
        },
        "TODTransfer": {
          "violations": [],
          "warnings": [],
          "safe": [],
          "conflicts": [
            -1,
            1190
          ]
        },
        "DAO": {
          "violations": [],
          "warnings": [
            1190
          ],
          "safe": [],
          "conflicts": []
        },
        "TODAmount": {
          "violations": [
            -1
          ],
          "warnings": [],
          "safe": [
            1190
          ],
          "conflicts": []
        },
        "MissingInputValidation": {
          "violations": [
            1190
          ],
          "warnings": [
            1190,
            1166
          ],
          "safe": [],
          "conflicts": []
        },
        "DAOConstantGas": {
          "violations": [],
          "warnings": [
            -1
          ],
          "safe": [],
          "conflicts": []
        },
        "UnrestrictedEtherFlow": {
          "violations": [],
          "warnings": [
            -1,
            1190,
            1226
          ],
          "safe": [],
          "conflicts": []
        }
      }
    }
  }
}